{"class": "CNNPolicy", "keras_model": "{\"class_name\": \"Sequential\", \"config\": [{\"class_name\": \"Convolution2D\", \"config\": {\"name\": \"convolution2d_1\", \"trainable\": true, \"batch_input_shape\": [null, 12, 19, 19], \"input_dtype\": \"float32\", \"nb_filter\": 128, \"nb_row\": 5, \"nb_col\": 5, \"init\": \"uniform\", \"activation\": \"relu\", \"border_mode\": \"same\", \"subsample\": [1, 1], \"dim_ordering\": \"th\", \"W_regularizer\": null, \"b_regularizer\": null, \"activity_regularizer\": null, \"W_constraint\": null, \"b_constraint\": null, \"bias\": true}}, {\"class_name\": \"Convolution2D\", \"config\": {\"name\": \"convolution2d_2\", \"trainable\": true, \"nb_filter\": 128, \"nb_row\": 3, \"nb_col\": 3, \"init\": \"uniform\", \"activation\": \"relu\", \"border_mode\": \"same\", \"subsample\": [1, 1], \"dim_ordering\": \"th\", \"W_regularizer\": null, \"b_regularizer\": null, \"activity_regularizer\": null, \"W_constraint\": null, \"b_constraint\": null, \"bias\": true}}, {\"class_name\": \"Convolution2D\", \"config\": {\"name\": \"convolution2d_3\", \"trainable\": true, \"nb_filter\": 128, \"nb_row\": 3, \"nb_col\": 3, \"init\": \"uniform\", \"activation\": \"relu\", \"border_mode\": \"same\", \"subsample\": [1, 1], \"dim_ordering\": \"th\", \"W_regularizer\": null, \"b_regularizer\": null, \"activity_regularizer\": null, \"W_constraint\": null, \"b_constraint\": null, \"bias\": true}}, {\"class_name\": \"Convolution2D\", \"config\": {\"name\": \"convolution2d_4\", \"trainable\": true, \"nb_filter\": 128, \"nb_row\": 3, \"nb_col\": 3, \"init\": \"uniform\", \"activation\": \"relu\", \"border_mode\": \"same\", \"subsample\": [1, 1], \"dim_ordering\": \"th\", \"W_regularizer\": null, \"b_regularizer\": null, \"activity_regularizer\": null, \"W_constraint\": null, \"b_constraint\": null, \"bias\": true}}, {\"class_name\": \"Convolution2D\", \"config\": {\"name\": \"convolution2d_5\", \"trainable\": true, \"nb_filter\": 128, \"nb_row\": 3, \"nb_col\": 3, \"init\": \"uniform\", \"activation\": \"relu\", \"border_mode\": \"same\", \"subsample\": [1, 1], \"dim_ordering\": \"th\", \"W_regularizer\": null, \"b_regularizer\": null, \"activity_regularizer\": null, \"W_constraint\": null, \"b_constraint\": null, \"bias\": true}}, {\"class_name\": \"Convolution2D\", \"config\": {\"name\": \"convolution2d_6\", \"trainable\": true, \"nb_filter\": 128, \"nb_row\": 3, \"nb_col\": 3, \"init\": \"uniform\", \"activation\": \"relu\", \"border_mode\": \"same\", \"subsample\": [1, 1], \"dim_ordering\": \"th\", \"W_regularizer\": null, \"b_regularizer\": null, \"activity_regularizer\": null, \"W_constraint\": null, \"b_constraint\": null, \"bias\": true}}, {\"class_name\": \"Convolution2D\", \"config\": {\"name\": \"convolution2d_7\", \"trainable\": true, \"nb_filter\": 128, \"nb_row\": 3, \"nb_col\": 3, \"init\": \"uniform\", \"activation\": \"relu\", \"border_mode\": \"same\", \"subsample\": [1, 1], \"dim_ordering\": \"th\", \"W_regularizer\": null, \"b_regularizer\": null, \"activity_regularizer\": null, \"W_constraint\": null, \"b_constraint\": null, \"bias\": true}}, {\"class_name\": \"Convolution2D\", \"config\": {\"name\": \"convolution2d_8\", \"trainable\": true, \"nb_filter\": 128, \"nb_row\": 3, \"nb_col\": 3, \"init\": \"uniform\", \"activation\": \"relu\", \"border_mode\": \"same\", \"subsample\": [1, 1], \"dim_ordering\": \"th\", \"W_regularizer\": null, \"b_regularizer\": null, \"activity_regularizer\": null, \"W_constraint\": null, \"b_constraint\": null, \"bias\": true}}, {\"class_name\": \"Convolution2D\", \"config\": {\"name\": \"convolution2d_9\", \"trainable\": true, \"nb_filter\": 128, \"nb_row\": 3, \"nb_col\": 3, \"init\": \"uniform\", \"activation\": \"relu\", \"border_mode\": \"same\", \"subsample\": [1, 1], \"dim_ordering\": \"th\", \"W_regularizer\": null, \"b_regularizer\": null, \"activity_regularizer\": null, \"W_constraint\": null, \"b_constraint\": null, \"bias\": true}}, {\"class_name\": \"Convolution2D\", \"config\": {\"name\": \"convolution2d_10\", \"trainable\": true, \"nb_filter\": 128, \"nb_row\": 3, \"nb_col\": 3, \"init\": \"uniform\", \"activation\": \"relu\", \"border_mode\": \"same\", \"subsample\": [1, 1], \"dim_ordering\": \"th\", \"W_regularizer\": null, \"b_regularizer\": null, \"activity_regularizer\": null, \"W_constraint\": null, \"b_constraint\": null, \"bias\": true}}, {\"class_name\": \"Convolution2D\", \"config\": {\"name\": \"convolution2d_11\", \"trainable\": true, \"nb_filter\": 128, \"nb_row\": 3, \"nb_col\": 3, \"init\": \"uniform\", \"activation\": \"relu\", \"border_mode\": \"same\", \"subsample\": [1, 1], \"dim_ordering\": \"th\", \"W_regularizer\": null, \"b_regularizer\": null, \"activity_regularizer\": null, \"W_constraint\": null, \"b_constraint\": null, \"bias\": true}}, {\"class_name\": \"Convolution2D\", \"config\": {\"name\": \"convolution2d_12\", \"trainable\": true, \"nb_filter\": 128, \"nb_row\": 3, \"nb_col\": 3, \"init\": \"uniform\", \"activation\": \"relu\", \"border_mode\": \"same\", \"subsample\": [1, 1], \"dim_ordering\": \"th\", \"W_regularizer\": null, \"b_regularizer\": null, \"activity_regularizer\": null, \"W_constraint\": null, \"b_constraint\": null, \"bias\": true}}, {\"class_name\": \"Convolution2D\", \"config\": {\"name\": \"convolution2d_13\", \"trainable\": true, \"nb_filter\": 1, \"nb_row\": 1, \"nb_col\": 1, \"init\": \"uniform\", \"activation\": \"linear\", \"border_mode\": \"same\", \"subsample\": [1, 1], \"dim_ordering\": \"th\", \"W_regularizer\": null, \"b_regularizer\": null, \"activity_regularizer\": null, \"W_constraint\": null, \"b_constraint\": null, \"bias\": true}}, {\"class_name\": \"Flatten\", \"config\": {\"name\": \"flatten_1\", \"trainable\": true}}, {\"class_name\": \"Bias\", \"config\": {\"name\": \"bias_1\", \"trainable\": true}}, {\"class_name\": \"Activation\", \"config\": {\"name\": \"activation_1\", \"trainable\": true, \"activation\": \"softmax\"}}], \"keras_version\": \"1.2.0\"}", "feature_list": ["board", "ones", "turns_since"]}